aiorate/__init__.py
aiorate/rate.py
aiorate-1.0.2.dist-info/LICENSE
aiorate-1.0.2.dist-info/WHEEL
aiorate-1.0.2.dist-info/METADATA
aiorate-1.0.2.dist-info/RECORD
