Metadata-Version: 2.1
Name: aiorate
Version: 1.0.2
Summary: Loop frequency regulator for asyncio.
Keywords: rate,loop,frequency,regulator
Author-email: Stéphane Caron <stephane.caron@normalesup.org>
Maintainer-email: Stéphane Caron <stephane.caron@normalesup.org>
Requires-Python: >=3.7
Classifier: Development Status :: 5 - Production/Stable
Classifier: Intended Audience :: Developers
Classifier: Intended Audience :: Science/Research
Classifier: License :: OSI Approved :: Apache Software License
Classifier: Operating System :: OS Independent
Classifier: Programming Language :: Python :: 3
Classifier: Programming Language :: Python :: 3.8
Classifier: Programming Language :: Python :: 3.9
Classifier: Topic :: Scientific/Engineering :: Mathematics
Requires-Dist: sphinx ; extra == "doc"
Project-URL: Changelog, https://github.com/tasts-robots/aiorate/blob/master/CHANGELOG.md
Project-URL: Documentation, https://tasts-robots.org/doc/aiorate/
Project-URL: Source, https://github.com/tasts-robots/aiorate
Project-URL: Tracker, https://github.com/tasts-robots/aiorate/issues
Provides-Extra: doc
